{"type":"header","name":"t:sections.header.settings.header-group.label","sections":{"announcement-bar":{"type":"announcement-bar","settings":{"height":50,"height_mobile":40,"color_scheme":"","text":"Seit über 350 Jahren und 13 Generationen im Familienbesitz⎥☎️ <a href=\"tel:+4967315471021\" title=\"tel:+4967315471021\">+49 6731 - 54 71 021<\/a>⎥✉️ <a href=\"mailto:info@petershof.com\" target=\"_blank\" title=\"mailto:info@petershof.com\">info@petershof.com<\/a>"}},"header":{"type":"header","blocks":{"mega_menu_6xD9bc":{"type":"mega_menu","settings":{"mega_menu_trigger":"shop","height":"sm","small_menu":"","show_mega_menu_1":true,"color_scheme_1":"background-4","description_1":"","heading_1":"Unser Jahrgangspaket","image_1":"shopify:\/\/shop_images\/titel.webp","overlay_opacity_1":0.3,"show_button":true,"button_style":"primary","button_label":"Jetzt bestellen","button_link":"shopify:\/\/products\/weingut-petershof-jahrgangspaket-2024-25"}}},"block_order":["mega_menu_6xD9bc"],"custom_css":[".categories-list__image img,.categories-list__image svg.placeholder-svg {width: 100%; height: 100%; object-fit: scale-down; object-position: right;}"],"settings":{"enable_border":true,"header_type":"center-logo","logo":"shopify:\/\/shop_images\/3.png","logo_2":"shopify:\/\/shop_images\/Weingut_Petershof_Logo_weiss.png","logo_width":155,"menu":"main-menu","small_menu":"","enable_country_selector":false,"enable_language_selector":true,"enable_social":true,"sticky_header_type":"always","enable_search":true,"show_search_promo":false,"show_collection_card":true,"collection_list":["bestseller","frontpage","spirituosen","weinpakete","weissweine"],"show_search_block":false,"search_color_scheme":"","search_subheading":"","search_heading":"Heading","button_link":"","button_label":"Button label","button_style":"primary","overlay_opacity":0,"show_search_block_2":false,"search_color_scheme_2":"","search_subheading_2":"","search_heading_2":"Heading","button_link_2":"","button_label_2":"Button label","button_style_2":"primary","overlay_opacity_2":0}}},"order":["announcement-bar","header"]}